Encryption/__init__.py
Encryption/encryption_V2.py
Expon_Encryption-0.1.dist-info/METADATA
Expon_Encryption-0.1.dist-info/WHEEL
Expon_Encryption-0.1.dist-info/top_level.txt
Expon_Encryption-0.1.dist-info/RECORD
